{
  "generator-jhipster": {
    "promptValues": {
      "packageName": "com.ibm.sp.gateway"
    },
    "jhipsterVersion": "6.4.1",
    "applicationType": "gateway",
    "baseName": "gateway",
    "packageName": "com.ibm.sp.gateway",
    "packageFolder": "com/ibm/sp/gateway",
    "serverPort": "9099",
    "authenticationType": "jwt",
    "cacheProvider": "ehcache",
    "enableHibernateCache": true,
    "websocket": false,
    "databaseType": "sql",
    "devDatabaseType": "h2Disk",
    "prodDatabaseType": "mysql",
    "searchEngine": false,
    "messageBroker": false,
    "serviceDiscoveryType": "eureka",
    "buildTool": "maven",
    "enableSwaggerCodegen": false,
    "jwtSecretKey": "MjZlYzY4OTcxNWNjMDEwNWIyMWI3YjMyNTc1ODc2Y2NiOWY1YjZmMWE1MjczZjc0ZWZiNzhiOTBmZmM5MDYxNjY3ZDc1NTYzODE4OTE3ODcwZDZkMDFmNTdlYTVlNjg0ODU3NjMxMjdiYjAwZmEyNDliZGE3ZGM2YzBiMjFjZDE=",
    "embeddableLaunchScript": false,
    "useSass": true,
    "clientPackageManager": "npm",
    "clientFramework": "react",
    "clientTheme": "cerulean",
    "clientThemeVariant": "primary",
    "testFrameworks": [
      "gatling"
    ],
    "jhiPrefix": "jhi",
    "entitySuffix": "",
    "dtoSuffix": "DTO",
    "otherModules": [
      {
        "name": "generator-jhipster-docker",
        "version": "2.5.0"
      }
    ],
    "enableTranslation": false,
    "blueprints": []
  }
}