{
    "name": "Training",
    "fields": [
        {
            "fieldName": "status",
            "fieldType": "TrainStatus",
            "fieldValues": "Active,Inactive",
            "fieldValidateRules": [
                "required"
            ]
        },
        {
            "fieldName": "name",
            "fieldType": "String",
            "fieldValidateRules": [
                "required"
            ]
        },
        {
            "fieldName": "commissionAmount",
            "fieldType": "Float",
            "fieldValidateRules": [
                "required"
            ]
        },
        {
            "fieldName": "avgRating",
            "fieldType": "Float"
        },
        {
            "fieldName": "startDate",
            "fieldType": "Instant"
        },
        {
            "fieldName": "endDate",
            "fieldType": "Instant"
        },
        {
            "fieldName": "mentorId",
            "fieldType": "Long"
        },
        {
            "fieldName": "mentorName",
            "fieldType": "String"
        },
        {
            "fieldName": "skillName",
            "fieldType": "String",
            "fieldValidateRules": [
                "required"
            ]
        },
        {
            "fieldName": "remarks",
            "fieldType": "String"
        }
    ],
    "relationships": [],
    "changelogDate": "20191031115426",
    "javadoc": "Training entity.\\n@author full stack trainning laidongshi.",
    "entityTableName": "training",
    "dto": "no",
    "pagination": "no",
    "service": "serviceImpl",
    "jpaMetamodelFiltering": false,
    "fluentMethods": true,
    "readOnly": false,
    "clientRootFolder": "",
    "applications": "*"
}